concat_module.v
module concat_module
    #(parameter BIT_SIZE=16)
(
    input wire[BIT_SIZE-1:0] left,
    input wire[3:0] digit,
    output reg[BIT_SIZE-1:0] out,
    output reg error
);

reg [BIT_SIZE-1:0] result;
always @(*) begin
    result <= (left * 4'd10) + digit;
    error <= (result < left) ? 1'b1 : 1'b0;
    out <= result;
end

endmodule

src/modules/fsm_module/concat_module/concat_module_tb.v
`timescale 1ns/1ps

module concat_module_tb;

reg [14:0] left;
reg [3:0] digit;
wire [14:0] result;
wire error;

concat_module #(.BIT_SIZE(15)) concat_dut (left, digit, result, error);

initial begin
    left = 4'd1;
    digit = 1'd1;
end

always
    #20 left = result;

initial begin
    $dumpfile("waveform.vcd"); 
    $dumpvars(1);

    #200 $finish;
end
 


endmodule

src/modules/fsm_module/concat_module/waveform.vcd
$date
	Thu Jun 26 11:31:38 2025
$end
$version
	Icarus Verilog
$end
$timescale
	1ps
$end
$scope module concat_module_tb $end
$var wire 15 ! result [14:0] $end
$var wire 1 " error $end
$var reg 4 # digit [3:0] $end
$var reg 15 $ left [14:0] $end
$upscope $end
$enddefinitions $end
$comment Show the parameter values. $end
$dumpall
$end
#0
$dumpvars
b1 $
b1 #
0"
b1011 !
$end
#20000
b1101111 !
b1011 $
#40000
b10001010111 !
b1101111 $
#60000
b10101101100111 !
b10001010111 $
#80000
b11001000000111 !
b10101101100111 $
#100000
b111010001000111 !
b11001000000111 $
#120000
b101011000111 !
1"
b111010001000111 $
#140000
b110101111000111 !
0"
b101011000111 $
#160000
b11010111000111 !
1"
b110101111000111 $
#180000
b1100111000111 !
1"
b11010111000111 $
#200000
b111000111 !
1"
b1100111000111 $
